exgeneralis/__init__.py
exgeneralis/main.py
exgeneralis-0.1rc0.dist-info/METADATA
exgeneralis-0.1rc0.dist-info/WHEEL
exgeneralis-0.1rc0.dist-info/licenses/LICENSE
exgeneralis-0.1rc0.dist-info/licenses/LICENSE.md
exgeneralis-0.1rc0.dist-info/RECORD
